capmonstercloudclient/CapMonsterCloudClient.py
capmonstercloudclient/GetResultTimeouts.py
capmonstercloudclient/__init__.py
capmonstercloudclient/captchaResult.py
capmonstercloudclient/clientOptions.py
capmonstercloudclient/exceptions.py
capmonstercloudclient/requestController.py
capmonstercloudclient/utils.py
capmonstercloudclient/version.txt
capmonstercloudclient/requests/AltchaCustomTaskRequest.py
capmonstercloudclient/requests/AmazonWafRequest.py
capmonstercloudclient/requests/BasiliskCustomTaskRequest.py
capmonstercloudclient/requests/BinanceTaskRequest.py
capmonstercloudclient/requests/ComplexImageTaskBase.py
capmonstercloudclient/requests/CustomTaskRequestBase.py
capmonstercloudclient/requests/DataDomeCustomTaskRequest.py
capmonstercloudclient/requests/FuncaptchaComplexImageTask.py
capmonstercloudclient/requests/FuncaptchaRequest.py
capmonstercloudclient/requests/GeetestRequest.py
capmonstercloudclient/requests/HcaptchaComplexImageTask.py
capmonstercloudclient/requests/HcaptchaRequest.py
capmonstercloudclient/requests/ImageToTextRequest.py
capmonstercloudclient/requests/ImpervaCustomTaskRequest.py
capmonstercloudclient/requests/MTCaptchaRequest.py
capmonstercloudclient/requests/ProsopoTaskRequest.py
capmonstercloudclient/requests/RecaptchaComplexImageTask.py
capmonstercloudclient/requests/RecaptchaV2EnterpiseRequest.py
capmonstercloudclient/requests/RecaptchaV2Request.py
capmonstercloudclient/requests/RecaptchaV3EnterpriseRequest.py
capmonstercloudclient/requests/RecaptchaV3ProxylessRequest.py
capmonstercloudclient/requests/RecognitionComplexImageTaskRequest.py
capmonstercloudclient/requests/TemuCustomTaskRequest.py
capmonstercloudclient/requests/TenDiCustomTaskRequest.py
capmonstercloudclient/requests/TurnstileRequest.py
capmonstercloudclient/requests/YidunRequest.py
capmonstercloudclient/requests/__init__.py
capmonstercloudclient/requests/baseRequest.py
capmonstercloudclient/requests/baseRequestWithProxy.py
capmonstercloudclient/requests/enums.py
capmonstercloudclient-3.4.0.dist-info/licenses/LICENSE
capmonstercloudclient-3.4.0.dist-info/METADATA
capmonstercloudclient-3.4.0.dist-info/WHEEL
capmonstercloudclient-3.4.0.dist-info/top_level.txt
capmonstercloudclient-3.4.0.dist-info/RECORD
