Metadata-Version: 2.4
Name: capmonstercloudclient
Version: 3.4.0
Summary: Official CapMonsterCloud Client: https://capmonster.cloud/
Home-page: https://github.com/ZennoLab/capmonstercloud-client-python
Author: Andrey Ilyin
Author-email: andrey.ilyin@zennolab.com
License: AGPL-3.0
Keywords: captcha 
Classifier: License :: OSI Approved :: GNU Affero General Public License v3 or later (AGPLv3+)
Classifier: Programming Language :: Python
Classifier: Programming Language :: Python :: 3
Classifier: Programming Language :: Python :: 3 :: Only
Classifier: Programming Language :: Python :: 3.6
Classifier: Programming Language :: Python :: 3.7
Classifier: Programming Language :: Python :: 3.8
Classifier: Programming Language :: Python :: 3.9
Classifier: Programming Language :: Python :: 3.10
Classifier: Development Status :: 5 - Production/Stable
Classifier: Framework :: AsyncIO
Classifier: Operating System :: Unix
Classifier: Operating System :: Microsoft :: Windows
Classifier: Operating System :: MacOS
Requires-Python: >=3.6
License-File: LICENSE
Requires-Dist: aiohappyeyeballs==2.4.4; python_version >= "3.9" and python_version <= "3.13"
Requires-Dist: aiohttp==3.11.10; python_version >= "3.9" and python_version <= "3.13"
Requires-Dist: aiosignal==1.3.1; python_version >= "3.9" and python_version <= "3.13"
Requires-Dist: annotated-types==0.7.0; python_version >= "3.9" and python_version <= "3.13"
Requires-Dist: async-timeout==5.0.1; python_version >= "3.9" and python_version <= "3.11"
Requires-Dist: attrs==24.2.0; python_version >= "3.9" and python_version <= "3.13"
Requires-Dist: frozenlist==1.5.0; python_version >= "3.9" and python_version <= "3.13"
Requires-Dist: idna==3.10; python_version >= "3.9" and python_version <= "3.13"
Requires-Dist: multidict==6.1.0; python_version >= "3.9" and python_version <= "3.13"
Requires-Dist: propcache==0.2.1; python_version >= "3.9" and python_version <= "3.13"
Requires-Dist: pydantic-core==2.27.1; python_version >= "3.9" and python_version <= "3.13"
Requires-Dist: pydantic==2.10.3; python_version >= "3.9" and python_version <= "3.13"
Requires-Dist: typing-extensions==4.12.2; python_version >= "3.9" and python_version <= "3.13"
Requires-Dist: yarl==1.18.3; python_version >= "3.9" and python_version <= "3.13"
Requires-Dist: aiohttp==3.7.4; python_version >= "3.6" and python_version <= "3.8"
Requires-Dist: pydantic==2.10.3; python_version >= "3.8" and python_version < "3.9"
Requires-Dist: pydantic==2.5.3; python_version >= "3.7" and python_version < "3.8"
Requires-Dist: pydantic==2.1.*; python_version < "3.7"
Dynamic: author
Dynamic: author-email
Dynamic: classifier
Dynamic: description
Dynamic: description-content-type
Dynamic: home-page
Dynamic: keywords
Dynamic: license
Dynamic: license-file
Dynamic: requires-dist
Dynamic: requires-python
Dynamic: summary
